surfhub/__init__.py
surfhub/utils.py
surfhub/cache/__init__.py
surfhub/cache/base.py
surfhub/scraper/__init__.py
surfhub/scraper/browserless.py
surfhub/scraper/crawlbase.py
surfhub/scraper/local.py
surfhub/scraper/model.py
surfhub/scraper/zyte.py
surfhub/serper/__init__.py
surfhub/serper/duckduckgo.py
surfhub/serper/google.py
surfhub/serper/model.py
surfhub/serper/serpapi.py
surfhub/serper/serper.py
surfhub/serper/tavily.py
surfhub/serper/valueserp.py
surfhub-0.0.5.dist-info/METADATA
surfhub-0.0.5.dist-info/WHEEL
surfhub-0.0.5.dist-info/top_level.txt
surfhub-0.0.5.dist-info/RECORD
