Metadata-Version: 2.4
Name: surfhub
Version: 0.0.5
Summary: A Python library for SERP and web scraping with multiple provider integration
Home-page: https://github.com/nqbao/surfhub
Author: Bao Nguyen
Author-email: qbao.nguyen@gmail.com
Project-URL: Bug Tracker, https://github.com/nqbao/surfhub/issues
Keywords: serp,scraping,web,browserless,zyte
Classifier: Programming Language :: Python :: 3
Classifier: License :: OSI Approved :: MIT License
Classifier: Operating System :: OS Independent
Requires-Python: >=3.6
Requires-Dist: requests>=2.25.1
Requires-Dist: beautifulsoup4>=4.9.3
Requires-Dist: httpx>=0.27.2
Requires-Dist: pydantic>=1.10.13
Requires-Dist: diskcache>=5.6.3
Provides-Extra: test
Requires-Dist: respx; extra == "test"
